Metadata-Version: 1.0
Name: mosinDistributions
Version: 0.1
Summary: Gaussian and Binomial distributions
Home-page: UNKNOWN
Author: Mosin Mahajan
Author-email: mosinmahajan@gmail.com
License: UNKNOWN
Platform: UNKNOWN
